fasthtml_hf/__init__.py
fasthtml_hf/backup.py
fasthtml_hf/deploy.py
fasthtml_hf-0.1.5.dist-info/LICENSE
fasthtml_hf-0.1.5.dist-info/METADATA
fasthtml_hf-0.1.5.dist-info/WHEEL
fasthtml_hf-0.1.5.dist-info/entry_points.txt
fasthtml_hf-0.1.5.dist-info/top_level.txt
fasthtml_hf-0.1.5.dist-info/RECORD
