Metadata-Version: 2.1
Name: fasthtml-hf
Version: 0.1.5
Summary: Huggingface deployment for FastHTML
Author-email: Jeremy Howard <info@fast.ai>, Freddy Boulton <info@fast.ai>
License: Apache License
Project-URL: Homepage, https://github.com/AnswerDotAI/fasthtml-hf
Classifier: Development Status :: 3 - Alpha
Classifier: Intended Audience :: Developers
Classifier: License :: OSI Approved :: Apache Software License
Requires-Python: <4,>=3.7
License-File: LICENSE
Requires-Dist: fastcore
Requires-Dist: huggingface-hub
